compilers/__init__.py
compilers/base.py
compilers/basic_compiler.py
compilers/logo_compiler.py
compilers/pilot_compiler.py
core/__init__.py
core/framework.py
core/interpreter.py
core/audio/__init__.py
core/audio/engine.py
core/debugging/__init__.py
core/debugging/error_analyzer.py
core/debugging/performance_monitor.py
core/debugging/test_framework.py
core/debugging/visual_debugger.py
core/editor/__init__.py
core/editor/code_completion.py
core/editor/code_completion_engine.py
core/editor/code_formatter.py
core/editor/compiler_manager.py
core/editor/enhanced_editor.py
core/editor/language_engine.py
core/editor/syntax_analyzer.py
core/hardware/__init__.py
core/hardware/devices.py
core/iot/__init__.py
core/iot/devices.py
core/language/__init__.py
core/language/interpreter.py
core/language/james_compiler.py
core/language/lexer.py
core/language/parser.py
core/language/compiler/__init__.py
core/language/compiler/codegen.py
core/language/compiler/lexer.py
core/language/compiler/optimizer.py
core/language/compiler/parser.py
core/language/errors/__init__.py
core/language/errors/error_manager.py
core/language/handlers/__init__.py
core/language/handlers/logo_handler.py
core/language/handlers/pilot_handler.py
core/language/handlers/python_handler.py
core/language/plugins/__init__.py
core/language/plugins/base.py
core/language/plugins/loader.py
core/language/plugins/manager.py
core/language/plugins/registry.py
core/language/runtime/__init__.py
core/language/runtime/engine.py
core/language/runtime/modes.py
core/language/runtime/variables.py
core/language/stdlib/core.py
core/language/tests/__init__.py
core/language/tests/test_errors.py
core/language/tests/test_integration.py
core/language/tests/test_stdlib.py
core/languages/__init__.py
core/languages/basic.py
core/languages/javascript_executor.py
core/languages/logo.py
core/languages/perl.py
core/languages/pilot.py
core/languages/python_executor.py
core/networking/__init__.py
core/networking/collaboration.py
timewarp_ide-1.0.0.dist-info/licenses/LICENSE
timewarp_ide-1.0.0.dist-info/METADATA
timewarp_ide-1.0.0.dist-info/WHEEL
timewarp_ide-1.0.0.dist-info/entry_points.txt
timewarp_ide-1.0.0.dist-info/top_level.txt
timewarp_ide-1.0.0.dist-info/RECORD
