Metadata-Version: 2.4
Name: timewarp-ide
Version: 1.0.0
Summary: Educational Programming IDE with Multi-Language Support
Home-page: https://github.com/James-HoneyBadger/Time_Warp
Author: James-HoneyBadger
Author-email: TimeWarp Development Team <info@timewarp-ide.org>
Maintainer-email: James-HoneyBadger <timewarp-ide@example.com>
License: MIT
Project-URL: Homepage, https://github.com/James-HoneyBadger/Time_Warp
Project-URL: Documentation, https://timewarp-ide.readthedocs.io/
Project-URL: Repository, https://github.com/James-HoneyBadger/Time_Warp
Project-URL: Issues, https://github.com/James-HoneyBadger/Time_Warp/issues
Project-URL: Changelog, https://github.com/James-HoneyBadger/Time_Warp/blob/main/CHANGELOG.md
Keywords: education,programming,ide,basic,logo,pilot,compiler,turtle-graphics,educational
Classifier: Development Status :: 5 - Production/Stable
Classifier: Intended Audience :: Education
Classifier: Intended Audience :: Developers
Classifier: License :: OSI Approved :: MIT License
Classifier: Operating System :: OS Independent
Classifier: Programming Language :: Python :: 3
Classifier: Programming Language :: Python :: 3.9
Classifier: Programming Language :: Python :: 3.10
Classifier: Programming Language :: Python :: 3.11
Classifier: Programming Language :: Python :: 3.12
Classifier: Topic :: Education
Classifier: Topic :: Software Development :: Compilers
Classifier: Topic :: Software Development :: Interpreters
Requires-Python: >=3.9
License-File: LICENSE
Requires-Dist: Pillow>=8.0.0
Provides-Extra: dev
Requires-Dist: pytest>=7.0.0; extra == "dev"
Requires-Dist: pytest-cov>=4.0.0; extra == "dev"
Requires-Dist: black>=22.0.0; extra == "dev"
Requires-Dist: flake8>=4.0.0; extra == "dev"
Requires-Dist: mypy>=1.0.0; extra == "dev"
Requires-Dist: sphinx>=4.0.0; extra == "dev"
Requires-Dist: sphinx-rtd-theme>=1.0.0; extra == "dev"
Provides-Extra: docs
Requires-Dist: sphinx>=4.0.0; extra == "docs"
Requires-Dist: sphinx-rtd-theme>=1.0.0; extra == "docs"
Provides-Extra: graphics
Requires-Dist: Pillow>=8.0.0; extra == "graphics"
Provides-Extra: hardware
Requires-Dist: pyserial>=3.0; extra == "hardware"
Requires-Dist: smbus2>=0.4.0; extra == "hardware"
Dynamic: author
Dynamic: home-page
Dynamic: license-file
Dynamic: requires-python
